setup.py
ParsePy.egg-info/PKG-INFO
ParsePy.egg-info/SOURCES.txt
ParsePy.egg-info/dependency_links.txt
ParsePy.egg-info/pbr.json
ParsePy.egg-info/requires.txt
ParsePy.egg-info/top_level.txt
parse_rest/__init__.py
parse_rest/config.py
parse_rest/connection.py
parse_rest/core.py
parse_rest/datatypes.py
parse_rest/installation.py
parse_rest/query.py
parse_rest/role.py
parse_rest/tests.py
parse_rest/user.py
parse_rest/cloudcode/cloud/main.js