Metadata-Version: 1.1
Name: ParsePy
Version: 0.3.20150629
Summary: A client library for Parse.com'.s REST API
Home-page: https://github.com/nana-music/ParsePy
Author: kiri1120
Author-email: kazuki.s1120@gmail.com
License: UNKNOWN
Platform: UNKNOWN
Classifier: Development Status :: 5 - Production/Stable
Classifier: Environment :: Web Environment
Classifier: Intended Audience :: Developers
Classifier: License :: OSI Approved :: GNU General Public License v3 (GPLv3)
Classifier: Operating System :: OS Independent
Classifier: Programming Language :: Python :: 2.6
Classifier: Programming Language :: Python :: 2.7
Classifier: Programming Language :: Python :: 3.3
Classifier: Programming Language :: Python :: 3.4
